google_search_results-1.3.1.dist-info/DESCRIPTION.rst
google_search_results-1.3.1.dist-info/METADATA
google_search_results-1.3.1.dist-info/RECORD
google_search_results-1.3.1.dist-info/WHEEL
google_search_results-1.3.1.dist-info/metadata.json
google_search_results-1.3.1.dist-info/top_level.txt
lib/__init__.py
lib/google_search_results.py
