Metadata-Version: 1.2
Name: google-search-results
Version: 1.3.1
Summary: this pip package is meant to scrape and parse Google results using SERP API. Feel free to fork this repository to add more backends.
Home-page: https://github.com/serpapi/google-search-results-python
Author: lf2225
Author-email: lf2225@gmail.com
License: UNKNOWN
Platform: UNKNOWN
Classifier: License :: OSI Approved :: MIT License
Classifier: Programming Language :: Python :: 2.7
Requires-Python: >=2.6, !=3.0.*, !=3.1.*, !=3.2.*
